[{"D":70,"B":35,"L":1200,"qty":19,"section_group_id":"E1","section_group_id_and_qty":"E1 (x19)"},{"D":70,"B":35,"L":1500,"qty":75,"section_group_id":"E2","section_group_id_and_qty":"E2 (x75)"},{"D":70,"B":35,"L":1800,"qty":75,"section_group_id":"E3","section_group_id_and_qty":"E3 (x75)"},{"D":70,"B":35,"L":2100,"qty":23,"section_group_id":"E4","section_group_id_and_qty":"E4 (x23)"},{"D":70,"B":35,"L":2300,"qty":54,"section_group_id":"E5","section_group_id_and_qty":"E5 (x54)"},{"D":70,"B":35,"L":2700,"qty":36,"section_group_id":"E6","section_group_id_and_qty":"E6 (x36)"},{"D":70,"B":35,"L":3000,"qty":35,"section_group_id":"E7","section_group_id_and_qty":"E7 (x35)"},{"D":70,"B":35,"L":3300,"qty":11,"section_group_id":"E8","section_group_id_and_qty":"E8 (x11)"},{"D":70,"B":35,"L":3600,"qty":5,"section_group_id":"E9","section_group_id_and_qty":"E9 (x5)"},{"D":70,"B":35,"L":3900,"qty":3,"section_group_id":"E10","section_group_id_and_qty":"E10 (x3)"},{"D":70,"B":35,"L":4200,"qty":3,"section_group_id":"E11","section_group_id_and_qty":"E11 (x3)"},{"D":70,"B":35,"L":4500,"qty":1,"section_group_id":"E12","section_group_id_and_qty":"E12 (x1)"},{"D":90,"B":35,"L":1200,"qty":8,"section_group_id":"E13","section_group_id_and_qty":"E13 (x8)"},{"D":90,"B":35,"L":1500,"qty":9,"section_group_id":"E14","section_group_id_and_qty":"E14 (x9)"},{"D":90,"B":35,"L":1800,"qty":7,"section_group_id":"E15","section_group_id_and_qty":"E15 (x7)"},{"D":90,"B":35,"L":2100,"qty":8,"section_group_id":"E16","section_group_id_and_qty":"E16 (x8)"},{"D":90,"B":35,"L":2300,"qty":40,"section_group_id":"E17","section_group_id_and_qty":"E17 (x40)"},{"D":90,"B":35,"L":2400,"qty":25,"section_group_id":"E18","section_group_id_and_qty":"E18 (x25)"},{"D":90,"B":35,"L":2700,"qty":3,"section_group_id":"E19","section_group_id_and_qty":"E19 (x3)"},{"D":90,"B":35,"L":3000,"qty":6,"section_group_id":"E20","section_group_id_and_qty":"E20 (x6)"},{"D":90,"B":35,"L":2100,"qty":1,"section_group_id":"E21","section_group_id_and_qty":"E21 (x1)"},{"D":90,"B":35,"L":2300,"qty":11,"section_group_id":"E22","section_group_id_and_qty":"E22 (x11)"},{"D":90,"B":35,"L":3000,"qty":3,"section_group_id":"E23","section_group_id_and_qty":"E23 (x3)"},{"D":70,"B":35,"L":1200,"qty":11,"section_group_id":"E24","section_group_id_and_qty":"E24 (x11)"},{"D":70,"B":35,"L":1500,"qty":45,"section_group_id":"E25","section_group_id_and_qty":"E25 (x45)"},{"D":70,"B":35,"L":1800,"qty":45,"section_group_id":"E26","section_group_id_and_qty":"E26 (x45)"},{"D":70,"B":35,"L":2100,"qty":14,"section_group_id":"E27","section_group_id_and_qty":"E27 (x14)"},{"D":70,"B":35,"L":2300,"qty":32,"section_group_id":"E28","section_group_id_and_qty":"E28 (x32)"},{"D":70,"B":35,"L":2700,"qty":22,"section_group_id":"E29","section_group_id_and_qty":"E29 (x22)"},{"D":70,"B":35,"L":3000,"qty":21,"section_group_id":"E30","section_group_id_and_qty":"E30 (x21)"},{"D":70,"B":35,"L":3300,"qty":7,"section_group_id":"E31","section_group_id_and_qty":"E31 (x7)"},{"D":70,"B":35,"L":3600,"qty":3,"section_group_id":"E32","section_group_id_and_qty":"E32 (x3)"},{"D":70,"B":35,"L":3900,"qty":1,"section_group_id":"E33","section_group_id_and_qty":"E33 (x1)"},{"D":70,"B":35,"L":4200,"qty":2,"section_group_id":"E34","section_group_id_and_qty":"E34 (x2)"},{"D":90,"B":35,"L":1200,"qty":4,"section_group_id":"E35","section_group_id_and_qty":"E35 (x4)"},{"D":90,"B":35,"L":1500,"qty":5,"section_group_id":"E36","section_group_id_and_qty":"E36 (x5)"},{"D":90,"B":35,"L":1800,"qty":4,"section_group_id":"E37","section_group_id_and_qty":"E37 (x4)"},{"D":90,"B":35,"L":2100,"qty":5,"section_group_id":"E38","section_group_id_and_qty":"E38 (x5)"},{"D":90,"B":35,"L":2300,"qty":24,"section_group_id":"E39","section_group_id_and_qty":"E39 (x24)"},{"D":90,"B":35,"L":2400,"qty":15,"section_group_id":"E40","section_group_id_and_qty":"E40 (x15)"},{"D":90,"B":35,"L":2700,"qty":2,"section_group_id":"E41","section_group_id_and_qty":"E41 (x2)"},{"D":90,"B":35,"L":3000,"qty":4,"section_group_id":"E42","section_group_id_and_qty":"E42 (x4)"},{"D":90,"B":35,"L":2100,"qty":1,"section_group_id":"E43","section_group_id_and_qty":"E43 (x1)"},{"D":90,"B":35,"L":2300,"qty":7,"section_group_id":"E44","section_group_id_and_qty":"E44 (x7)"},{"D":90,"B":35,"L":3000,"qty":2,"section_group_id":"E45","section_group_id_and_qty":"E45 (x2)"},{"D":70,"B":35,"L":1200,"qty":4,"section_group_id":"E46","section_group_id_and_qty":"E46 (x4)"},{"D":70,"B":35,"L":1500,"qty":15,"section_group_id":"E47","section_group_id_and_qty":"E47 (x15)"},{"D":70,"B":35,"L":1800,"qty":15,"section_group_id":"E48","section_group_id_and_qty":"E48 (x15)"},{"D":70,"B":35,"L":2100,"qty":4,"section_group_id":"E49","section_group_id_and_qty":"E49 (x4)"},{"D":70,"B":35,"L":2300,"qty":11,"section_group_id":"E50","section_group_id_and_qty":"E50 (x11)"},{"D":70,"B":35,"L":2700,"qty":7,"section_group_id":"E51","section_group_id_and_qty":"E51 (x7)"},{"D":70,"B":35,"L":3000,"qty":7,"section_group_id":"E52","section_group_id_and_qty":"E52 (x7)"},{"D":70,"B":35,"L":3300,"qty":2,"section_group_id":"E53","section_group_id_and_qty":"E53 (x2)"},{"D":70,"B":35,"L":3600,"qty":1,"section_group_id":"E54","section_group_id_and_qty":"E54 (x1)"},{"D":70,"B":35,"L":4200,"qty":1,"section_group_id":"E55","section_group_id_and_qty":"E55 (x1)"},{"D":90,"B":35,"L":1200,"qty":1,"section_group_id":"E56","section_group_id_and_qty":"E56 (x1)"},{"D":90,"B":35,"L":1500,"qty":2,"section_group_id":"E57","section_group_id_and_qty":"E57 (x2)"},{"D":90,"B":35,"L":1800,"qty":1,"section_group_id":"E58","section_group_id_and_qty":"E58 (x1)"},{"D":90,"B":35,"L":2100,"qty":1,"section_group_id":"E59","section_group_id_and_qty":"E59 (x1)"},{"D":90,"B":35,"L":2300,"qty":8,"section_group_id":"E60","section_group_id_and_qty":"E60 (x8)"},{"D":90,"B":35,"L":2400,"qty":5,"section_group_id":"E61","section_group_id_and_qty":"E61 (x5)"},{"D":90,"B":35,"L":3000,"qty":1,"section_group_id":"E62","section_group_id_and_qty":"E62 (x1)"},{"D":90,"B":35,"L":2300,"qty":2,"section_group_id":"E63","section_group_id_and_qty":"E63 (x2)"},{"D":70,"B":35,"L":1200,"qty":3,"section_group_id":"E64","section_group_id_and_qty":"E64 (x3)"},{"D":70,"B":35,"L":1500,"qty":15,"section_group_id":"E65","section_group_id_and_qty":"E65 (x15)"},{"D":70,"B":35,"L":1800,"qty":15,"section_group_id":"E66","section_group_id_and_qty":"E66 (x15)"},{"D":70,"B":35,"L":2100,"qty":4,"section_group_id":"E67","section_group_id_and_qty":"E67 (x4)"},{"D":70,"B":35,"L":2300,"qty":10,"section_group_id":"E68","section_group_id_and_qty":"E68 (x10)"},{"D":70,"B":35,"L":2700,"qty":7,"section_group_id":"E69","section_group_id_and_qty":"E69 (x7)"},{"D":70,"B":35,"L":3000,"qty":7,"section_group_id":"E70","section_group_id_and_qty":"E70 (x7)"},{"D":70,"B":35,"L":3300,"qty":2,"section_group_id":"E71","section_group_id_and_qty":"E71 (x2)"},{"D":70,"B":35,"L":3600,"qty":1,"section_group_id":"E72","section_group_id_and_qty":"E72 (x1)"},{"D":90,"B":35,"L":1200,"qty":1,"section_group_id":"E73","section_group_id_and_qty":"E73 (x1)"},{"D":90,"B":35,"L":1500,"qty":2,"section_group_id":"E74","section_group_id_and_qty":"E74 (x2)"},{"D":90,"B":35,"L":1800,"qty":1,"section_group_id":"E75","section_group_id_and_qty":"E75 (x1)"},{"D":90,"B":35,"L":2100,"qty":1,"section_group_id":"E76","section_group_id_and_qty":"E76 (x1)"},{"D":90,"B":35,"L":2300,"qty":8,"section_group_id":"E77","section_group_id_and_qty":"E77 (x8)"},{"D":90,"B":35,"L":2400,"qty":5,"section_group_id":"E78","section_group_id_and_qty":"E78 (x5)"},{"D":90,"B":35,"L":3000,"qty":1,"section_group_id":"E79","section_group_id_and_qty":"E79 (x1)"},{"D":90,"B":35,"L":2300,"qty":2,"section_group_id":"E80","section_group_id_and_qty":"E80 (x2)"}]